QgisZhongwenWendang/README.md
QgisZhongwenWendang/__init__.py
QgisZhongwenWendang/__main__.py
QgisZhongwenWendang/file.epub
QgisZhongwenWendang/index.html
QgisZhongwenWendang/css/__init__.py
QgisZhongwenWendang/css/annotations.css
QgisZhongwenWendang/css/main.css
QgisZhongwenWendang/css/normalize.css
QgisZhongwenWendang/css/popup.css
QgisZhongwenWendang/font/__init__.py
QgisZhongwenWendang/font/fontello.eot
QgisZhongwenWendang/font/fontello.svg
QgisZhongwenWendang/font/fontello.ttf
QgisZhongwenWendang/font/fontello.woff
QgisZhongwenWendang/img/__init__.py
QgisZhongwenWendang/img/annotator-glyph-sprite.png
QgisZhongwenWendang/img/annotator-icon-sprite.png
QgisZhongwenWendang/img/apple-touch-icon.png
QgisZhongwenWendang/img/cancelfullscreen.png
QgisZhongwenWendang/img/close.png
QgisZhongwenWendang/img/fullscreen.png
QgisZhongwenWendang/img/loader.gif
QgisZhongwenWendang/img/menu-icon.png
QgisZhongwenWendang/img/save.png
QgisZhongwenWendang/img/saved.png
QgisZhongwenWendang/img/settings-s.png
QgisZhongwenWendang/img/settings.png
QgisZhongwenWendang/img/star.png
QgisZhongwenWendang/js/__init__.py
QgisZhongwenWendang/js/epub.js
QgisZhongwenWendang/js/epub.min.js
QgisZhongwenWendang/js/epub.min.map
QgisZhongwenWendang/js/hooks.min.js
QgisZhongwenWendang/js/hooks.min.map
QgisZhongwenWendang/js/reader.js
QgisZhongwenWendang/js/reader.js.map
QgisZhongwenWendang/js/reader.min.js
QgisZhongwenWendang/js/reader.min.map
QgisZhongwenWendang/js/hooks/__init__.py
QgisZhongwenWendang/js/hooks/extensions/__init__.py
QgisZhongwenWendang/js/hooks/extensions/highlight.js
QgisZhongwenWendang/js/libs/__init__.py
QgisZhongwenWendang/js/libs/jquery.min.js
QgisZhongwenWendang/js/libs/localforage.min.js
QgisZhongwenWendang/js/libs/screenfull.js
QgisZhongwenWendang/js/libs/screenfull.min.js
QgisZhongwenWendang/js/libs/zip.min.js
QgisZhongwenWendang/js/plugins/__init__.py
QgisZhongwenWendang/js/plugins/hypothesis.js
QgisZhongwenWendang/js/plugins/search.js
qgis_zhongwen_wendang-2024.3.5.0.dist-info/METADATA
qgis_zhongwen_wendang-2024.3.5.0.dist-info/WHEEL
qgis_zhongwen_wendang-2024.3.5.0.dist-info/entry_points.txt
qgis_zhongwen_wendang-2024.3.5.0.dist-info/top_level.txt
qgis_zhongwen_wendang-2024.3.5.0.dist-info/RECORD
